{
  "url": "https://api.github.com/repos/shap/shap/issues/1401",
  "repository_url": "https://api.github.com/repos/shap/shap",
  "labels_url": "https://api.github.com/repos/shap/shap/issues/1401/labels{/name}",
  "comments_url": "https://api.github.com/repos/shap/shap/issues/1401/comments",
  "events_url": "https://api.github.com/repos/shap/shap/issues/1401/events",
  "html_url": "https://github.com/shap/shap/issues/1401",
  "id": 690152606,
  "node_id": "MDU6SXNzdWU2OTAxNTI2MDY=",
  "number": 1401,
  "title": "Shap for LSTM - features as timestep",
  "user": {
    "login": "Lecia321",
    "id": 70585382,
    "node_id": "MDQ6VXNlcjcwNTg1Mzgy",
    "avatar_url": "https://avatars.githubusercontent.com/u/70585382?v=4",
    "gravatar_id": "",
    "url": "https://api.github.com/users/Lecia321",
    "html_url": "https://github.com/Lecia321",
    "followers_url": "https://api.github.com/users/Lecia321/followers",
    "following_url": "https://api.github.com/users/Lecia321/following{/other_user}",
    "gists_url": "https://api.github.com/users/Lecia321/gists{/gist_id}",
    "starred_url": "https://api.github.com/users/Lecia321/starred{/owner}{/repo}",
    "subscriptions_url": "https://api.github.com/users/Lecia321/subscriptions",
    "organizations_url": "https://api.github.com/users/Lecia321/orgs",
    "repos_url": "https://api.github.com/users/Lecia321/repos",
    "events_url": "https://api.github.com/users/Lecia321/events{/privacy}",
    "received_events_url": "https://api.github.com/users/Lecia321/received_events",
    "type": "User",
    "site_admin": false
  },
  "labels": [

  ],
  "state": "open",
  "locked": false,
  "assignee": null,
  "assignees": [

  ],
  "milestone": null,
  "comments": 4,
  "created_at": "2020-09-01T13:40:12Z",
  "updated_at": "2021-09-21T10:01:59Z",
  "closed_at": null,
  "author_association": "NONE",
  "active_lock_reason": null,
  "body": "Hi there,\r\n\r\nI would like guidance as to how can I go about using Shap to explain my model when I am inputting the features(29 of them) as timesteps. So my LSTM training set has shape (observations, 29, 1).\r\n\r\nReally appreciate your input.",
  "closed_by": null,
  "reactions": {
    "url": "https://api.github.com/repos/shap/shap/issues/1401/reactions",
    "total_count": 0,
    "+1": 0,
    "-1": 0,
    "laugh": 0,
    "hooray": 0,
    "confused": 0,
    "heart": 0,
    "rocket": 0,
    "eyes": 0
  },
  "timeline_url": "https://api.github.com/repos/shap/shap/issues/1401/timeline",
  "performed_via_github_app": null,
  "state_reason": null
}
