{
  "url": "https://api.github.com/repos/shap/shap/issues/2155",
  "repository_url": "https://api.github.com/repos/shap/shap",
  "labels_url": "https://api.github.com/repos/shap/shap/issues/2155/labels{/name}",
  "comments_url": "https://api.github.com/repos/shap/shap/issues/2155/comments",
  "events_url": "https://api.github.com/repos/shap/shap/issues/2155/events",
  "html_url": "https://github.com/shap/shap/pull/2155",
  "id": 981810641,
  "node_id": "MDExOlB1bGxSZXF1ZXN0NzIxNzY5Njk3",
  "number": 2155,
  "title": "Reinforcement Learning Example",
  "user": {
    "login": "dynamik1703",
    "id": 10382711,
    "node_id": "MDQ6VXNlcjEwMzgyNzEx",
    "avatar_url": "https://avatars.githubusercontent.com/u/10382711?v=4",
    "gravatar_id": "",
    "url": "https://api.github.com/users/dynamik1703",
    "html_url": "https://github.com/dynamik1703",
    "followers_url": "https://api.github.com/users/dynamik1703/followers",
    "following_url": "https://api.github.com/users/dynamik1703/following{/other_user}",
    "gists_url": "https://api.github.com/users/dynamik1703/gists{/gist_id}",
    "starred_url": "https://api.github.com/users/dynamik1703/starred{/owner}{/repo}",
    "subscriptions_url": "https://api.github.com/users/dynamik1703/subscriptions",
    "organizations_url": "https://api.github.com/users/dynamik1703/orgs",
    "repos_url": "https://api.github.com/users/dynamik1703/repos",
    "events_url": "https://api.github.com/users/dynamik1703/events{/privacy}",
    "received_events_url": "https://api.github.com/users/dynamik1703/received_events",
    "type": "User",
    "site_admin": false
  },
  "labels": [

  ],
  "state": "open",
  "locked": false,
  "assignee": null,
  "assignees": [

  ],
  "milestone": null,
  "comments": 1,
  "created_at": "2021-08-28T11:21:57Z",
  "updated_at": "2023-06-11T03:07:46Z",
  "closed_at": null,
  "author_association": "NONE",
  "active_lock_reason": null,
  "draft": false,
  "pull_request": {
    "url": "https://api.github.com/repos/shap/shap/pulls/2155",
    "html_url": "https://github.com/shap/shap/pull/2155",
    "diff_url": "https://github.com/shap/shap/pull/2155.diff",
    "patch_url": "https://github.com/shap/shap/pull/2155.patch",
    "merged_at": null
  },
  "body": "Hello everyone,\r\nReinforcement learning is becoming more widely used. The agent's learned decisions are not easy to interpret and therefore SHAP provides an excellent method for analysis.\r\n\r\nHere I have prepared a notebook as an example. \r\n\r\nI am looking forward to your feedback.\r\n\r\nKind regards\r\nRoman",
  "closed_by": null,
  "reactions": {
    "url": "https://api.github.com/repos/shap/shap/issues/2155/reactions",
    "total_count": 0,
    "+1": 0,
    "-1": 0,
    "laugh": 0,
    "hooray": 0,
    "confused": 0,
    "heart": 0,
    "rocket": 0,
    "eyes": 0
  },
  "timeline_url": "https://api.github.com/repos/shap/shap/issues/2155/timeline",
  "performed_via_github_app": null,
  "state_reason": null
}
