{
  "url": "https://api.github.com/repos/shap/shap/issues/2447",
  "repository_url": "https://api.github.com/repos/shap/shap",
  "labels_url": "https://api.github.com/repos/shap/shap/issues/2447/labels{/name}",
  "comments_url": "https://api.github.com/repos/shap/shap/issues/2447/comments",
  "events_url": "https://api.github.com/repos/shap/shap/issues/2447/events",
  "html_url": "https://github.com/shap/shap/pull/2447",
  "id": 1175989549,
  "node_id": "PR_kwDOBHDcK840xX1z",
  "number": 2447,
  "title": "fix old scatter plot, new image baselines",
  "user": {
    "login": "slundberg",
    "id": 3740613,
    "node_id": "MDQ6VXNlcjM3NDA2MTM=",
    "avatar_url": "https://avatars.githubusercontent.com/u/3740613?v=4",
    "gravatar_id": "",
    "url": "https://api.github.com/users/slundberg",
    "html_url": "https://github.com/slundberg",
    "followers_url": "https://api.github.com/users/slundberg/followers",
    "following_url": "https://api.github.com/users/slundberg/following{/other_user}",
    "gists_url": "https://api.github.com/users/slundberg/gists{/gist_id}",
    "starred_url": "https://api.github.com/users/slundberg/starred{/owner}{/repo}",
    "subscriptions_url": "https://api.github.com/users/slundberg/subscriptions",
    "organizations_url": "https://api.github.com/users/slundberg/orgs",
    "repos_url": "https://api.github.com/users/slundberg/repos",
    "events_url": "https://api.github.com/users/slundberg/events{/privacy}",
    "received_events_url": "https://api.github.com/users/slundberg/received_events",
    "type": "User",
    "site_admin": false
  },
  "labels": [

  ],
  "state": "closed",
  "locked": false,
  "assignee": null,
  "assignees": [

  ],
  "milestone": null,
  "comments": 0,
  "created_at": "2022-03-21T21:59:08Z",
  "updated_at": "2022-03-21T21:59:21Z",
  "closed_at": "2022-03-21T21:59:21Z",
  "author_association": "COLLABORATOR",
  "active_lock_reason": null,
  "draft": false,
  "pull_request": {
    "url": "https://api.github.com/repos/shap/shap/pulls/2447",
    "html_url": "https://github.com/shap/shap/pull/2447",
    "diff_url": "https://github.com/shap/shap/pull/2447.diff",
    "patch_url": "https://github.com/shap/shap/pull/2447.patch",
    "merged_at": null
  },
  "body": null,
  "closed_by": {
    "login": "slundberg",
    "id": 3740613,
    "node_id": "MDQ6VXNlcjM3NDA2MTM=",
    "avatar_url": "https://avatars.githubusercontent.com/u/3740613?v=4",
    "gravatar_id": "",
    "url": "https://api.github.com/users/slundberg",
    "html_url": "https://github.com/slundberg",
    "followers_url": "https://api.github.com/users/slundberg/followers",
    "following_url": "https://api.github.com/users/slundberg/following{/other_user}",
    "gists_url": "https://api.github.com/users/slundberg/gists{/gist_id}",
    "starred_url": "https://api.github.com/users/slundberg/starred{/owner}{/repo}",
    "subscriptions_url": "https://api.github.com/users/slundberg/subscriptions",
    "organizations_url": "https://api.github.com/users/slundberg/orgs",
    "repos_url": "https://api.github.com/users/slundberg/repos",
    "events_url": "https://api.github.com/users/slundberg/events{/privacy}",
    "received_events_url": "https://api.github.com/users/slundberg/received_events",
    "type": "User",
    "site_admin": false
  },
  "reactions": {
    "url": "https://api.github.com/repos/shap/shap/issues/2447/reactions",
    "total_count": 0,
    "+1": 0,
    "-1": 0,
    "laugh": 0,
    "hooray": 0,
    "confused": 0,
    "heart": 0,
    "rocket": 0,
    "eyes": 0
  },
  "timeline_url": "https://api.github.com/repos/shap/shap/issues/2447/timeline",
  "performed_via_github_app": null,
  "state_reason": null
}
