{
  "url": "https://api.github.com/repos/shap/shap/issues/2450",
  "repository_url": "https://api.github.com/repos/shap/shap",
  "labels_url": "https://api.github.com/repos/shap/shap/issues/2450/labels{/name}",
  "comments_url": "https://api.github.com/repos/shap/shap/issues/2450/comments",
  "events_url": "https://api.github.com/repos/shap/shap/issues/2450/events",
  "html_url": "https://github.com/shap/shap/pull/2450",
  "id": 1176535240,
  "node_id": "PR_kwDOBHDcK840zMC-",
  "number": 2450,
  "title": "MAINT update classifiers entry in setup.py",
  "user": {
    "login": "glemaitre",
    "id": 7454015,
    "node_id": "MDQ6VXNlcjc0NTQwMTU=",
    "avatar_url": "https://avatars.githubusercontent.com/u/7454015?v=4",
    "gravatar_id": "",
    "url": "https://api.github.com/users/glemaitre",
    "html_url": "https://github.com/glemaitre",
    "followers_url": "https://api.github.com/users/glemaitre/followers",
    "following_url": "https://api.github.com/users/glemaitre/following{/other_user}",
    "gists_url": "https://api.github.com/users/glemaitre/gists{/gist_id}",
    "starred_url": "https://api.github.com/users/glemaitre/starred{/owner}{/repo}",
    "subscriptions_url": "https://api.github.com/users/glemaitre/subscriptions",
    "organizations_url": "https://api.github.com/users/glemaitre/orgs",
    "repos_url": "https://api.github.com/users/glemaitre/repos",
    "events_url": "https://api.github.com/users/glemaitre/events{/privacy}",
    "received_events_url": "https://api.github.com/users/glemaitre/received_events",
    "type": "User",
    "site_admin": false
  },
  "labels": [

  ],
  "state": "closed",
  "locked": false,
  "assignee": null,
  "assignees": [

  ],
  "milestone": null,
  "comments": 2,
  "created_at": "2022-03-22T09:53:47Z",
  "updated_at": "2022-03-22T19:28:50Z",
  "closed_at": "2022-03-22T19:28:50Z",
  "author_association": "CONTRIBUTOR",
  "active_lock_reason": null,
  "draft": false,
  "pull_request": {
    "url": "https://api.github.com/repos/shap/shap/pulls/2450",
    "html_url": "https://github.com/shap/shap/pull/2450",
    "diff_url": "https://github.com/shap/shap/pull/2450.diff",
    "patch_url": "https://github.com/shap/shap/pull/2450.patch",
    "merged_at": "2022-03-22T19:28:50Z"
  },
  "body": "To be in line with the current continuous integration.",
  "closed_by": {
    "login": "slundberg",
    "id": 3740613,
    "node_id": "MDQ6VXNlcjM3NDA2MTM=",
    "avatar_url": "https://avatars.githubusercontent.com/u/3740613?v=4",
    "gravatar_id": "",
    "url": "https://api.github.com/users/slundberg",
    "html_url": "https://github.com/slundberg",
    "followers_url": "https://api.github.com/users/slundberg/followers",
    "following_url": "https://api.github.com/users/slundberg/following{/other_user}",
    "gists_url": "https://api.github.com/users/slundberg/gists{/gist_id}",
    "starred_url": "https://api.github.com/users/slundberg/starred{/owner}{/repo}",
    "subscriptions_url": "https://api.github.com/users/slundberg/subscriptions",
    "organizations_url": "https://api.github.com/users/slundberg/orgs",
    "repos_url": "https://api.github.com/users/slundberg/repos",
    "events_url": "https://api.github.com/users/slundberg/events{/privacy}",
    "received_events_url": "https://api.github.com/users/slundberg/received_events",
    "type": "User",
    "site_admin": false
  },
  "reactions": {
    "url": "https://api.github.com/repos/shap/shap/issues/2450/reactions",
    "total_count": 0,
    "+1": 0,
    "-1": 0,
    "laugh": 0,
    "hooray": 0,
    "confused": 0,
    "heart": 0,
    "rocket": 0,
    "eyes": 0
  },
  "timeline_url": "https://api.github.com/repos/shap/shap/issues/2450/timeline",
  "performed_via_github_app": null,
  "state_reason": null
}
