{
  "url": "https://api.github.com/repos/shap/shap/issues/2647",
  "repository_url": "https://api.github.com/repos/shap/shap",
  "labels_url": "https://api.github.com/repos/shap/shap/issues/2647/labels{/name}",
  "comments_url": "https://api.github.com/repos/shap/shap/issues/2647/comments",
  "events_url": "https://api.github.com/repos/shap/shap/issues/2647/events",
  "html_url": "https://github.com/shap/shap/issues/2647",
  "id": 1340704549,
  "node_id": "I_kwDOBHDcK85P6Ycl",
  "number": 2647,
  "title": "\"invalid value encountered in true_divide\" Warning on Dependence plot",
  "user": {
    "login": "rflameiro",
    "id": 52053058,
    "node_id": "MDQ6VXNlcjUyMDUzMDU4",
    "avatar_url": "https://avatars.githubusercontent.com/u/52053058?v=4",
    "gravatar_id": "",
    "url": "https://api.github.com/users/rflameiro",
    "html_url": "https://github.com/rflameiro",
    "followers_url": "https://api.github.com/users/rflameiro/followers",
    "following_url": "https://api.github.com/users/rflameiro/following{/other_user}",
    "gists_url": "https://api.github.com/users/rflameiro/gists{/gist_id}",
    "starred_url": "https://api.github.com/users/rflameiro/starred{/owner}{/repo}",
    "subscriptions_url": "https://api.github.com/users/rflameiro/subscriptions",
    "organizations_url": "https://api.github.com/users/rflameiro/orgs",
    "repos_url": "https://api.github.com/users/rflameiro/repos",
    "events_url": "https://api.github.com/users/rflameiro/events{/privacy}",
    "received_events_url": "https://api.github.com/users/rflameiro/received_events",
    "type": "User",
    "site_admin": false
  },
  "labels": [

  ],
  "state": "open",
  "locked": false,
  "assignee": null,
  "assignees": [

  ],
  "milestone": null,
  "comments": 0,
  "created_at": "2022-08-16T18:07:40Z",
  "updated_at": "2022-08-16T18:07:40Z",
  "closed_at": null,
  "author_association": "NONE",
  "active_lock_reason": null,
  "body": "I saw this Warning when creating a Dependence plot. The plot still shows, I just thought someone might want to look into it, as it seems to be a \"Division by zero\" Warning.\r\n\r\n```\r\nimport sklearn  # version 1.1.2\r\nimport shap  # version 0.41.0\r\nimport xgboost  # version 1.5.1\r\n\r\nX, y = shap.datasets.iris()\r\nX_train, X_test, y_train, y_test = sklearn.model_selection.train_test_split(X, y, test_size=0.2, random_state=0)\r\nmodel = xgboost.XGBClassifier(use_label_encoder=False).fit(X_train, y_train)\r\nexplainer = shap.TreeExplainer(model)\r\nshap_values = explainer.shap_values(X_test)\r\nshap.dependence_plot(2, \r\n                     shap_values[0], \r\n                     X_test.values, \r\n                     feature_names=X_test.columns)\r\n```\r\n\r\n",
  "closed_by": null,
  "reactions": {
    "url": "https://api.github.com/repos/shap/shap/issues/2647/reactions",
    "total_count": 0,
    "+1": 0,
    "-1": 0,
    "laugh": 0,
    "hooray": 0,
    "confused": 0,
    "heart": 0,
    "rocket": 0,
    "eyes": 0
  },
  "timeline_url": "https://api.github.com/repos/shap/shap/issues/2647/timeline",
  "performed_via_github_app": null,
  "state_reason": null
}
