{
  "url": "https://api.github.com/repos/shap/shap/issues/2987",
  "repository_url": "https://api.github.com/repos/shap/shap",
  "labels_url": "https://api.github.com/repos/shap/shap/issues/2987/labels{/name}",
  "comments_url": "https://api.github.com/repos/shap/shap/issues/2987/comments",
  "events_url": "https://api.github.com/repos/shap/shap/issues/2987/events",
  "html_url": "https://github.com/shap/shap/pull/2987",
  "id": 1755447506,
  "node_id": "PR_kwDOBHDcK85S6tbD",
  "number": 2987,
  "title": "fix ntree_limit deprecation warning in _tree.py",
  "user": {
    "login": "adnene-guessoum",
    "id": 85586056,
    "node_id": "MDQ6VXNlcjg1NTg2MDU2",
    "avatar_url": "https://avatars.githubusercontent.com/u/85586056?v=4",
    "gravatar_id": "",
    "url": "https://api.github.com/users/adnene-guessoum",
    "html_url": "https://github.com/adnene-guessoum",
    "followers_url": "https://api.github.com/users/adnene-guessoum/followers",
    "following_url": "https://api.github.com/users/adnene-guessoum/following{/other_user}",
    "gists_url": "https://api.github.com/users/adnene-guessoum/gists{/gist_id}",
    "starred_url": "https://api.github.com/users/adnene-guessoum/starred{/owner}{/repo}",
    "subscriptions_url": "https://api.github.com/users/adnene-guessoum/subscriptions",
    "organizations_url": "https://api.github.com/users/adnene-guessoum/orgs",
    "repos_url": "https://api.github.com/users/adnene-guessoum/repos",
    "events_url": "https://api.github.com/users/adnene-guessoum/events{/privacy}",
    "received_events_url": "https://api.github.com/users/adnene-guessoum/received_events",
    "type": "User",
    "site_admin": false
  },
  "labels": [

  ],
  "state": "closed",
  "locked": false,
  "assignee": null,
  "assignees": [

  ],
  "milestone": null,
  "comments": 1,
  "created_at": "2023-06-13T18:32:33Z",
  "updated_at": "2023-06-14T02:29:38Z",
  "closed_at": "2023-06-14T02:29:38Z",
  "author_association": "CONTRIBUTOR",
  "active_lock_reason": null,
  "draft": false,
  "pull_request": {
    "url": "https://api.github.com/repos/shap/shap/pulls/2987",
    "html_url": "https://github.com/shap/shap/pull/2987",
    "diff_url": "https://github.com/shap/shap/pull/2987.diff",
    "patch_url": "https://github.com/shap/shap/pull/2987.patch",
    "merged_at": "2023-06-14T02:29:38Z"
  },
  "body": "## Overview\r\n\r\nDescription of the changes proposed in this pull request:\r\n\r\nRelated to issue https://github.com/slundberg/shap/issues/2984#issuecomment-1589509879 . \r\n\r\nfixes the deprecation warning mentionned in the issue by using iteration_range instead of ntree_limit as advised by xgboost documentation since version 1.4 ( https://github.com/dmlc/xgboost/releases/tag/v1.4.0 ).\r\n\r\n## Checklist\r\n\r\n- [x] Closes #2984 \r\n- [x] All [pre-commit checks](https://pre-commit.com/#install) pass.\r\n- [ ] Unit tests added (if fixing a bug or adding a new feature)\r\n- [x] Added entry to `CHANGELOG.md` (if changes will affect users)\r\n",
  "closed_by": {
    "login": "thatlittleboy",
    "id": 30731072,
    "node_id": "MDQ6VXNlcjMwNzMxMDcy",
    "avatar_url": "https://avatars.githubusercontent.com/u/30731072?v=4",
    "gravatar_id": "",
    "url": "https://api.github.com/users/thatlittleboy",
    "html_url": "https://github.com/thatlittleboy",
    "followers_url": "https://api.github.com/users/thatlittleboy/followers",
    "following_url": "https://api.github.com/users/thatlittleboy/following{/other_user}",
    "gists_url": "https://api.github.com/users/thatlittleboy/gists{/gist_id}",
    "starred_url": "https://api.github.com/users/thatlittleboy/starred{/owner}{/repo}",
    "subscriptions_url": "https://api.github.com/users/thatlittleboy/subscriptions",
    "organizations_url": "https://api.github.com/users/thatlittleboy/orgs",
    "repos_url": "https://api.github.com/users/thatlittleboy/repos",
    "events_url": "https://api.github.com/users/thatlittleboy/events{/privacy}",
    "received_events_url": "https://api.github.com/users/thatlittleboy/received_events",
    "type": "User",
    "site_admin": false
  },
  "reactions": {
    "url": "https://api.github.com/repos/shap/shap/issues/2987/reactions",
    "total_count": 0,
    "+1": 0,
    "-1": 0,
    "laugh": 0,
    "hooray": 0,
    "confused": 0,
    "heart": 0,
    "rocket": 0,
    "eyes": 0
  },
  "timeline_url": "https://api.github.com/repos/shap/shap/issues/2987/timeline",
  "performed_via_github_app": null,
  "state_reason": null
}
