{
  "url": "https://api.github.com/repos/shap/shap/issues/499",
  "repository_url": "https://api.github.com/repos/shap/shap",
  "labels_url": "https://api.github.com/repos/shap/shap/issues/499/labels{/name}",
  "comments_url": "https://api.github.com/repos/shap/shap/issues/499/comments",
  "events_url": "https://api.github.com/repos/shap/shap/issues/499/events",
  "html_url": "https://github.com/shap/shap/issues/499",
  "id": 423372589,
  "node_id": "MDU6SXNzdWU0MjMzNzI1ODk=",
  "number": 499,
  "title": "KernelExplainer Error if keep_index = True",
  "user": {
    "login": "mattivi",
    "id": 1651448,
    "node_id": "MDQ6VXNlcjE2NTE0NDg=",
    "avatar_url": "https://avatars.githubusercontent.com/u/1651448?v=4",
    "gravatar_id": "",
    "url": "https://api.github.com/users/mattivi",
    "html_url": "https://github.com/mattivi",
    "followers_url": "https://api.github.com/users/mattivi/followers",
    "following_url": "https://api.github.com/users/mattivi/following{/other_user}",
    "gists_url": "https://api.github.com/users/mattivi/gists{/gist_id}",
    "starred_url": "https://api.github.com/users/mattivi/starred{/owner}{/repo}",
    "subscriptions_url": "https://api.github.com/users/mattivi/subscriptions",
    "organizations_url": "https://api.github.com/users/mattivi/orgs",
    "repos_url": "https://api.github.com/users/mattivi/repos",
    "events_url": "https://api.github.com/users/mattivi/events{/privacy}",
    "received_events_url": "https://api.github.com/users/mattivi/received_events",
    "type": "User",
    "site_admin": false
  },
  "labels": [

  ],
  "state": "open",
  "locked": false,
  "assignee": null,
  "assignees": [

  ],
  "milestone": null,
  "comments": 1,
  "created_at": "2019-03-20T17:11:04Z",
  "updated_at": "2023-08-26T08:36:17Z",
  "closed_at": null,
  "author_association": "NONE",
  "active_lock_reason": null,
  "body": "When running shap.KernelExplainer with the option keep_index = True, there is the following error:\r\n\r\n```\r\nexplainer = shap.KernelExplainer(predict_AE_XAI_SHAP_API, X_real_XAI, keep_index = True)\r\nexplainer\r\n\r\n......./python3.6/site-packages/shap/explainers/kernel.py in __init__(self, model, data, link, **kwargs)\r\n    123         # see if we have a vector output\r\n    124         self.vector_out = True\r\n--> 125         if len(self.fnull.shape) == 0:\r\n    126             self.vector_out = False\r\n    127             self.fnull = np.array([self.fnull])\r\n\r\nAttributeError: 'float' object has no attribute 'shape'\r\n```\r\n\r\nAny idea?",
  "closed_by": null,
  "reactions": {
    "url": "https://api.github.com/repos/shap/shap/issues/499/reactions",
    "total_count": 1,
    "+1": 1,
    "-1": 0,
    "laugh": 0,
    "hooray": 0,
    "confused": 0,
    "heart": 0,
    "rocket": 0,
    "eyes": 0
  },
  "timeline_url": "https://api.github.com/repos/shap/shap/issues/499/timeline",
  "performed_via_github_app": null,
  "state_reason": null
}
