{
  "url": "https://api.github.com/repos/shap/shap/issues/730",
  "repository_url": "https://api.github.com/repos/shap/shap",
  "labels_url": "https://api.github.com/repos/shap/shap/issues/730/labels{/name}",
  "comments_url": "https://api.github.com/repos/shap/shap/issues/730/comments",
  "events_url": "https://api.github.com/repos/shap/shap/issues/730/events",
  "html_url": "https://github.com/shap/shap/issues/730",
  "id": 477303712,
  "node_id": "MDU6SXNzdWU0NzczMDM3MTI=",
  "number": 730,
  "title": "Keras example on KernelExplainer not working",
  "user": {
    "login": "doramir",
    "id": 20622722,
    "node_id": "MDQ6VXNlcjIwNjIyNzIy",
    "avatar_url": "https://avatars.githubusercontent.com/u/20622722?v=4",
    "gravatar_id": "",
    "url": "https://api.github.com/users/doramir",
    "html_url": "https://github.com/doramir",
    "followers_url": "https://api.github.com/users/doramir/followers",
    "following_url": "https://api.github.com/users/doramir/following{/other_user}",
    "gists_url": "https://api.github.com/users/doramir/gists{/gist_id}",
    "starred_url": "https://api.github.com/users/doramir/starred{/owner}{/repo}",
    "subscriptions_url": "https://api.github.com/users/doramir/subscriptions",
    "organizations_url": "https://api.github.com/users/doramir/orgs",
    "repos_url": "https://api.github.com/users/doramir/repos",
    "events_url": "https://api.github.com/users/doramir/events{/privacy}",
    "received_events_url": "https://api.github.com/users/doramir/received_events",
    "type": "User",
    "site_admin": false
  },
  "labels": [

  ],
  "state": "closed",
  "locked": false,
  "assignee": null,
  "assignees": [

  ],
  "milestone": null,
  "comments": 3,
  "created_at": "2019-08-06T10:38:32Z",
  "updated_at": "2019-08-27T08:20:35Z",
  "closed_at": "2019-08-11T16:07:20Z",
  "author_association": "CONTRIBUTOR",
  "active_lock_reason": null,
  "body": "I'm trying to run the example notebook `Census income classification with Keras` from this repo and I'm using shap version 0.29.3 and Keras 2.2.4\r\n im getting an error\r\n```python\r\n---------------------------------------------------------------------------\r\nTypeError                                 Traceback (most recent call last)\r\n<ipython-input-5-a6b5b5903508> in <module>()\r\n      1 explainer = shap.KernelExplainer(f, X.iloc[:50,:])\r\n      2 shap_values = explainer.shap_values(X.iloc[299,:], nsamples=500)\r\n----> 3 shap.force_plot(explainer.expected_value, shap_values, X_display.iloc[299,:])\r\n\r\n/usr/local/lib/python3.7/site-packages/shap/plots/force.py in force_plot(base_value, shap_values, features, feature_names, out_names, link, plot_cmap, matplotlib, show, figsize, ordering_keys, ordering_keys_time_format, text_rotation)\r\n     61 \r\n     62     # auto unwrap the base_value\r\n---> 63     if type(base_value) == np.ndarray and len(base_value) == 1:\r\n     64         base_value = base_value[0]\r\n     65 \r\n\r\nTypeError: len() of unsized object\r\n\r\n````\r\n\r\nanyone know why? and how to solve it? \r\nThanks!",
  "closed_by": {
    "login": "doramir",
    "id": 20622722,
    "node_id": "MDQ6VXNlcjIwNjIyNzIy",
    "avatar_url": "https://avatars.githubusercontent.com/u/20622722?v=4",
    "gravatar_id": "",
    "url": "https://api.github.com/users/doramir",
    "html_url": "https://github.com/doramir",
    "followers_url": "https://api.github.com/users/doramir/followers",
    "following_url": "https://api.github.com/users/doramir/following{/other_user}",
    "gists_url": "https://api.github.com/users/doramir/gists{/gist_id}",
    "starred_url": "https://api.github.com/users/doramir/starred{/owner}{/repo}",
    "subscriptions_url": "https://api.github.com/users/doramir/subscriptions",
    "organizations_url": "https://api.github.com/users/doramir/orgs",
    "repos_url": "https://api.github.com/users/doramir/repos",
    "events_url": "https://api.github.com/users/doramir/events{/privacy}",
    "received_events_url": "https://api.github.com/users/doramir/received_events",
    "type": "User",
    "site_admin": false
  },
  "reactions": {
    "url": "https://api.github.com/repos/shap/shap/issues/730/reactions",
    "total_count": 0,
    "+1": 0,
    "-1": 0,
    "laugh": 0,
    "hooray": 0,
    "confused": 0,
    "heart": 0,
    "rocket": 0,
    "eyes": 0
  },
  "timeline_url": "https://api.github.com/repos/shap/shap/issues/730/timeline",
  "performed_via_github_app": null,
  "state_reason": "completed"
}
